_version.py
pytest_flakefighters/__init__.py
pytest_flakefighters/database_management.py
pytest_flakefighters/function_coverage.py
pytest_flakefighters/main.py
pytest_flakefighters/plugin.py
pytest_flakefighters/rerun_strategies.py
pytest_flakefighters/flakefighters/__init__.py
pytest_flakefighters/flakefighters/abstract_flakefighter.py
pytest_flakefighters/flakefighters/coverage_independence.py
pytest_flakefighters/flakefighters/deflaker.py
pytest_flakefighters/flakefighters/traceback_matching.py
pytest_flakefighters-0.1.6.dist-info/licenses/LICENSE
pytest_flakefighters-0.1.6.dist-info/METADATA
pytest_flakefighters-0.1.6.dist-info/WHEEL
pytest_flakefighters-0.1.6.dist-info/entry_points.txt
pytest_flakefighters-0.1.6.dist-info/top_level.txt
pytest_flakefighters-0.1.6.dist-info/RECORD
