Metadata-Version: 2.4
Name: pytest-flakefighters
Version: 0.1.6
Summary: Pytest plugin implementing flaky test failure detection and classification.
Author: TestFLARE Team
Project-URL: Repository, https://github.com/test-flare/pytest-flakefighters
Requires-Python: <3.14,>=3.10
License-File: LICENSE
Requires-Dist: pytest>=6.2.0
Requires-Dist: coverage>=7.10.6
Requires-Dist: GitPython>=3.1.45
Requires-Dist: unidiff>=0.7.5
Requires-Dist: sqlalchemy>=2.0.43
Requires-Dist: dotenv>=0.9.9
Requires-Dist: pandas
Requires-Dist: scipy<=1.15
Requires-Dist: pyyaml>=6
Requires-Dist: scikit-learn>=1.7
Requires-Dist: nltk>=3.9
Provides-Extra: dev
Requires-Dist: black; extra == "dev"
Requires-Dist: pytest-cov; extra == "dev"
Requires-Dist: pylint; extra == "dev"
Requires-Dist: pre_commit; extra == "dev"
Requires-Dist: sphinx-autoapi; extra == "dev"
Requires-Dist: sphinx_rtd_theme; extra == "dev"
Requires-Dist: tox>=4.31.0; extra == "dev"
Requires-Dist: myst_parser; extra == "dev"
Requires-Dist: nbsphinx; extra == "dev"
Dynamic: license-file
